{
    "edctype": "dataspaceconnector:datarequest",
    "protocol": "ids-multipart",
    "assetId": "sample-asset-id",
    "contractId": "1:d97d4ce1-eda7-4296-95d1-1afdab9447e1",
    "dataDestination": {
        "properties": {
            "path": "/Users/agmangas/Desktop/edcpoc.json",
            "keyName": "keyName",
            "type": "jsonfile"
        }
    },
    "transferType": {
        "contentType": "application/octet-stream",
        "isFinite": true
    },
    "managedResources": false,
    "connectorAddress": "http://localhost:8282/api/v1/ids/data",
    "connectorId": "consumer"
}